siwe_auth/__init__.py
siwe_auth/admin.py
siwe_auth/apps.py
siwe_auth/backend.py
siwe_auth/custom_groups/__init__.py
siwe_auth/custom_groups/erc1155.py
siwe_auth/custom_groups/erc20.py
siwe_auth/custom_groups/erc721.py
siwe_auth/custom_groups/group_manager.py
siwe_auth/migrations/0001_initial.py
siwe_auth/migrations/0002_alter_wallet_created.py
siwe_auth/migrations/__init__.py
siwe_auth/models.py
siwe_auth/static/siwe_auth/js/login.js
siwe_auth/static/siwe_auth/js/login.js.LICENSE.txt
siwe_auth/templates/siwe_auth/login.html
siwe_auth/urls.py
siwe_auth/utils/__init__.py
siwe_auth/views.py
django_siwe_auth-0.3.2.dist-info/LICENSE.txt
django_siwe_auth-0.3.2.dist-info/WHEEL
django_siwe_auth-0.3.2.dist-info/METADATA
django_siwe_auth-0.3.2.dist-info/RECORD
