Metadata-Version: 2.1
Name: django-siwe-auth
Version: 0.3.2
Summary: Custom Django authentication backend using Sign-In with Ethereum (EIP-4361) with a custom wallet user model.
Home-page: https://github.com/payton/django-siwe-auth
License: MIT
Keywords: SIWE,EIP-4361,Sign-In with Ethereum,Django,Web3,Authentication,Authorization
Author: Payton Garland
Author-email: payton.r.g@gmail.com
Requires-Python: >=3.8,<4.0
Classifier: License :: OSI Approved :: MIT License
Classifier: Programming Language :: Python :: 3
Classifier: Programming Language :: Python :: 3.10
Classifier: Programming Language :: Python :: 3.8
Classifier: Programming Language :: Python :: 3.9
Requires-Dist: Django (>=4.0.1,<5.0.0)
Requires-Dist: django-ratelimit (>=3.0.1,<4.0.0)
Requires-Dist: pytz (>=2021.3,<2022.0)
Requires-Dist: siwe (>=1.0.0,<2.0.0)
Requires-Dist: web3 (>=5.26.0,<6.0.0)
Project-URL: Repository, https://github.com/payton/django-siwe-auth
